mangapark_dl/__init__.py
mangapark_dl/mangapark_dl.py
mangapark_dl-0.0.3.dist-info/LICENSE
mangapark_dl-0.0.3.dist-info/METADATA
mangapark_dl-0.0.3.dist-info/WHEEL
mangapark_dl-0.0.3.dist-info/entry_points.txt
mangapark_dl-0.0.3.dist-info/RECORD
