Metadata-Version: 2.3
Name: mangapark-dl
Version: 0.0.3
Summary: A folder/cbz downloader for manga from mangapark v5.3. Uses chrome OR safari drivers via selenium.
License: Unlicense
Author: Etash J
Author-email: etashjhanji@gmail.com
Requires-Python: >=3.9
Classifier: Programming Language :: Python :: 3
Classifier: Operating System :: OS Independent
Requires-Dist: alive_progress
Requires-Dist: pillow
Requires-Dist: requests
Requires-Dist: selenium
Project-URL: Homepage, https://github.com/etashj/mangapark-dl
Project-URL: Issues, https://github.com/etashj/mangapark-dl/issues
